CHANGES.rst
LICENSE
MANIFEST.in
README.rst
setup.cfg
setup.py
sphinxcontrib/__init__.py
sphinxcontrib/lassodomain.py
sphinxcontrib_lassodomain.egg-info/PKG-INFO
sphinxcontrib_lassodomain.egg-info/SOURCES.txt
sphinxcontrib_lassodomain.egg-info/dependency_links.txt
sphinxcontrib_lassodomain.egg-info/namespace_packages.txt
sphinxcontrib_lassodomain.egg-info/not-zip-safe
sphinxcontrib_lassodomain.egg-info/requires.txt
sphinxcontrib_lassodomain.egg-info/top_level.txt