Metadata-Version: 1.1
Name: sphinxcontrib-lassodomain
Version: 0.1
Summary: Lasso domain for Sphinx
Home-page: http://bitbucket.org/birkenfeld/sphinx-contrib
Author: Eric Knibbe
Author-email: eric at lassosoft dotcom
License: BSD
Download-URL: http://pypi.python.org/pypi/sphinxcontrib-lassodomain
Platform: any
Classifier: Development Status :: 4 - Beta
Classifier: Environment :: Console
Classifier: Environment :: Web Environment
Classifier: Intended Audience :: Developers
Classifier: License :: OSI Approved :: BSD License
Classifier: Operating System :: OS Independent
Classifier: Programming Language :: Python
Classifier: Topic :: Documentation
Classifier: Topic :: Utilities
